{"cameraMode":{"drawMode":0,"name":"Shaded","section":"Shading Mode"},"sceneLighting":true,"audioPlay":false,"sceneViewState":{"m_AlwaysRefresh":false,"showFog":true,"showSkybox":true,"showFlares":true,"showImageEffects":true,"showParticleSystems":true,"showVisualEffectGraphs":true,"m_FxEnabled":true},"in2DMode":false,"pivot":{"x":29.480546951293947,"y":-7.978764533996582,"z":-1.5791597366333008},"rotation":{"x":-0.0954495444893837,"y":-0.7366126775741577,"z":0.10635827481746674,"w":-0.6610516905784607},"size":18.439254760742189,"orthographic":false}